skbio_parasail/__init__.py
scikit-bio-parasail/__version__.py
scikit_bio_parasail-0.0.4.dist-info/WHEEL
scikit_bio_parasail-0.0.4.dist-info/METADATA
scikit_bio_parasail-0.0.4.dist-info/licenses/LICENSE
scikit_bio_parasail-0.0.4.dist-info/RECORD
