Metadata-Version: 2.1
Name: scikit-bio-parasail
Version: 0.0.4
License: BSD-3-Clause
Author-email: Andrew Robbins & Joris Vankerschaver <andrew@robbinsa.me>
Requires-Python: >=3.8,<3.12
Requires-Dist: parasail>=1.2.4
Requires-Dist: scikit-bio>=0.5.7
Project-URL: Homepage, https://github.com/theAeon/scikit-bio-parasail
